<?xml version="1.0" encoding="UTF-8" ?>

<PropertyList>


 <path>Mall_of_Asia_Wheel.ac</path>



 
<animation>
  <type>rotate</type>
  
  <object-name>Wheel1</object-name>
  <object-name>Wheel2</object-name>
  <object-name>Wheel3</object-name>
  <object-name>Car1</object-name>
  <object-name>Car2</object-name>
  <object-name>Car3</object-name>
  <object-name>Car4</object-name>
  <object-name>Car5</object-name>
  <object-name>Car6</object-name>
  <object-name>Car7</object-name>
  <object-name>Car8</object-name>
  <object-name>Car9</object-name>
  <object-name>Car10</object-name>
  <object-name>Car11</object-name>
  <object-name>Car12</object-name>
  <object-name>Car13</object-name>
  <object-name>Car14</object-name>
  <object-name>Car15</object-name>
  <object-name>Car16</object-name>
  <object-name>Car17</object-name>
  <object-name>Car18</object-name>
  <object-name>Car19</object-name>
  <object-name>Car20</object-name>
  <object-name>Car21</object-name>
  <object-name>Car22</object-name>
  <object-name>Car23</object-name>
  <object-name>Car24</object-name>
  <object-name>Car25</object-name>
  <object-name>Car26</object-name>
  <object-name>Car27</object-name>
  <object-name>Car28</object-name>
  <object-name>Car29</object-name>
  <object-name>Car30</object-name>
  <object-name>Car31</object-name>
  <object-name>Car32</object-name>
  <object-name>Car33</object-name>
  <object-name>Car34</object-name>
  <object-name>Car35</object-name>
  <object-name>Car36</object-name>
  
<property>/sim/time/elapsed-sec</property>

  <factor>-2.0</factor>

  <center>

   <x-m>0.0</x-m>

   <y-m>0.0</y-m>

   <z-m>29.24</z-m>

  </center>

  <axis>

   <x>0</x>

   <y>1</y>

   <z>0</z>

  </axis>

 </animation>

 <animation>

  <type>rotate</type>

  <object-name>Car1</object-name>
  <property>/sim/time/elapsed-sec</property>

  <factor>-2.0</factor>

  <center>

   <x-m>4.45</x-m>

   <y-m>0</y-m>

   <z-m>54.47</z-m>

  </center>

  <axis>

   <x>0</x>

   <y>-1</y>

   <z>0</z>

  </axis>

 </animation>

 <animation>

  <type>rotate</type>

  <object-name>Car2</object-name>
  <property>/sim/time/elapsed-sec</property>

  <factor>-2.0</factor>

  <center>

   <x-m>8.83</x-m>

   <y-m>0</y-m>

   <z-m>53.3</z-m>

  </center>

  <axis>

   <x>0</x>

   <y>-1</y>

   <z>0</z>

  </axis>

 </animation>
 <animation>

  <type>rotate</type>

  <object-name>Car3</object-name>
  <property>/sim/time/elapsed-sec</property>

  <factor>-2.0</factor>

  <center>

   <x-m>12.96</x-m>

   <y-m>0</y-m>

   <z-m>51.29</z-m>

  </center>

  <axis>

   <x>0</x>

   <y>-1</y>

   <z>0</z>

  </axis>

 </animation>
 <animation>

  <type>rotate</type>

  <object-name>Car4</object-name>
  <property>/sim/time/elapsed-sec</property>

  <factor>-2.0</factor>

  <center>

   <x-m>16.64</x-m>

   <y-m>0</y-m>

   <z-m>48.71</z-m>

  </center>

  <axis>

   <x>0</x>

   <y>-1</y>

   <z>0</z>

  </axis>

 </animation>
 <animation>

  <type>rotate</type>

  <object-name>Car5</object-name>
  <property>/sim/time/elapsed-sec</property>

  <factor>-2.0</factor>

  <center>

   <x-m>19.72</x-m>

   <y-m>0</y-m>

   <z-m>45.50</z-m>

  </center>

  <axis>

   <x>0</x>

   <y>-1</y>

   <z>0</z>

  </axis>

 </animation>
 <animation>

  <type>rotate</type>

  <object-name>Car6</object-name>
  <property>/sim/time/elapsed-sec</property>

  <factor>-2.0</factor>

  <center>

   <x-m>22.26</x-m>

   <y-m>0</y-m>

   <z-m>41.83</z-m>

  </center>

  <axis>

   <x>0</x>

   <y>-1</y>

   <z>0</z>

  </axis>

 </animation>
 <animation>

  <type>rotate</type>

  <object-name>Car7</object-name>
  <property>/sim/time/elapsed-sec</property>

  <factor>-2.0</factor>

  <center>

   <x-m>24.05</x-m>

   <y-m>0</y-m>

   <z-m>37.82</z-m>

  </center>

  <axis>

   <x>0</x>

   <y>-1</y>

   <z>0</z>

  </axis>

 </animation>
 <animation>

  <type>rotate</type>

  <object-name>Car8</object-name>
  <property>/sim/time/elapsed-sec</property>

  <factor>-2.0</factor>

  <center>

   <x-m>25.17</x-m>

   <y-m>0</y-m>

   <z-m>33.40</z-m>

  </center>

  <axis>

   <x>0</x>

   <y>-1</y>

   <z>0</z>

  </axis>

 </animation>
 <animation>

  <type>rotate</type>

  <object-name>Car9</object-name>
  <property>/sim/time/elapsed-sec</property>

  <factor>-2.0</factor>

  <center>

   <x-m>25.47</x-m>

   <y-m>0</y-m>

   <z-m>29.02</z-m>

  </center>

  <axis>

   <x>0</x>

   <y>-1</y>

   <z>0</z>

  </axis>

 </animation>
 <animation>

  <type>rotate</type>

  <object-name>Car10</object-name>
  <property>/sim/time/elapsed-sec</property>

  <factor>-2.0</factor>

  <center>

   <x-m>25.16</x-m>

   <y-m>0</y-m>

   <z-m>24.81</z-m>

  </center>

  <axis>

   <x>0</x>

   <y>-1</y>

   <z>0</z>

  </axis>

 </animation>
 <animation>

  <type>rotate</type>

  <object-name>Car11</object-name>
  <property>/sim/time/elapsed-sec</property>

  <factor>-2.0</factor>

  <center>

   <x-m>23.93</x-m>

   <y-m>0</y-m>

   <z-m>20.50</z-m>

  </center>

  <axis>

   <x>0</x>

   <y>-1</y>

   <z>0</z>

  </axis>

 </animation>
 <animation>

  <type>rotate</type>

  <object-name>Car12</object-name>
  <property>/sim/time/elapsed-sec</property>

  <factor>-2.0</factor>

  <center>

   <x-m>22.09</x-m>

   <y-m>0</y-m>

   <z-m>16.44</z-m>

  </center>

  <axis>

   <x>0</x>

   <y>-1</y>

   <z>0</z>

  </axis>

 </animation>
 <animation>

  <type>rotate</type>

  <object-name>Car13</object-name>
  <property>/sim/time/elapsed-sec</property>

  <factor>-2.0</factor>

  <center>

   <x-m>19.56</x-m>

   <y-m>0</y-m>

   <z-m>12.79</z-m>

  </center>

  <axis>

   <x>0</x>

   <y>-1</y>

   <z>0</z>

  </axis>

 </animation>
 <animation>

  <type>rotate</type>

  <object-name>Car14</object-name>
  <property>/sim/time/elapsed-sec</property>

  <factor>-2.0</factor>

  <center>

   <x-m>16.43</x-m>

   <y-m>0</y-m>

   <z-m>9.61</z-m>

  </center>

  <axis>

   <x>0</x>

   <y>-1</y>

   <z>0</z>

  </axis>

 </animation>
 <animation>

  <type>rotate</type>

  <object-name>Car15</object-name>
  <property>/sim/time/elapsed-sec</property>

  <factor>-2.0</factor>

  <center>

   <x-m>12.80</x-m>

   <y-m>0</y-m>

   <z-m>7.12</z-m>

  </center>

  <axis>

   <x>0</x>

   <y>-1</y>

   <z>0</z>

  </axis>

 </animation>
 <animation>

  <type>rotate</type>

  <object-name>Car16</object-name>
  <property>/sim/time/elapsed-sec</property>

  <factor>-2.0</factor>

  <center>

   <x-m>8.74</x-m>

   <y-m>0</y-m>

   <z-m>5.18</z-m>

  </center>

  <axis>

   <x>0</x>

   <y>-1</y>

   <z>0</z>

  </axis>

 </animation>
 <animation>

  <type>rotate</type>

  <object-name>Car17</object-name>
  <property>/sim/time/elapsed-sec</property>

  <factor>-2.0</factor>

  <center>

   <x-m>4.46</x-m>

   <y-m>0</y-m>

   <z-m>4.01</z-m>

  </center>

  <axis>

   <x>0</x>

   <y>-1</y>

   <z>0</z>

  </axis>

 </animation>
 <animation>

  <type>rotate</type>

  <object-name>Car18</object-name>
  <property>/sim/time/elapsed-sec</property>

  <factor>-2.0</factor>

  <center>

   <x-m>0</x-m>

   <y-m>0</y-m>

   <z-m>3.62</z-m>

  </center>

  <axis>

   <x>0</x>

   <y>-1</y>

   <z>0</z>

  </axis>

 </animation>
 <animation>

  <type>rotate</type>

  <object-name>Car19</object-name>
  <property>/sim/time/elapsed-sec</property>

  <factor>-2.0</factor>

  <center>

   <x-m>-4.45</x-m>

   <y-m>0</y-m>

   <z-m>4.01</z-m>

  </center>

  <axis>

   <x>0</x>

   <y>-1</y>

   <z>0</z>

  </axis>

 </animation>
 <animation>

  <type>rotate</type>

  <object-name>Car20</object-name>
  <property>/sim/time/elapsed-sec</property>

  <factor>-2.0</factor>

  <center>

   <x-m>-8.80</x-m>

   <y-m>0</y-m>

   <z-m>5.20</z-m>

  </center>

  <axis>

   <x>0</x>

   <y>-1</y>

   <z>0</z>

  </axis>

 </animation>
 <animation>

  <type>rotate</type>

  <object-name>Car21</object-name>
  <property>/sim/time/elapsed-sec</property>

  <factor>-2.0</factor>

  <center>

   <x-m>-12.79</x-m>

   <y-m>0</y-m>

   <z-m>7.11</z-m>

  </center>

  <axis>

   <x>0</x>

   <y>-1</y>

   <z>0</z>

  </axis>

 </animation>
 <animation>

  <type>rotate</type>

  <object-name>Car22</object-name>
  <property>/sim/time/elapsed-sec</property>

  <factor>-2.0</factor>

  <center>

   <x-m>-16.43</x-m>

   <y-m>0</y-m>

   <z-m>9.63</z-m>

  </center>

  <axis>

   <x>0</x>

   <y>-1</y>

   <z>0</z>

  </axis>

 </animation>
 <animation>

  <type>rotate</type>

  <object-name>Car23</object-name>
  <property>/sim/time/elapsed-sec</property>

  <factor>-2.0</factor>

  <center>

   <x-m>-19.61</x-m>

   <y-m>0</y-m>

   <z-m>12.76</z-m>

  </center>

  <axis>

   <x>0</x>

   <y>-1</y>

   <z>0</z>

  </axis>

 </animation>
 <animation>

  <type>rotate</type>

  <object-name>Car24</object-name>
  <property>/sim/time/elapsed-sec</property>

  <factor>-2.0</factor>

  <center>

   <x-m>-22.17</x-m>

   <y-m>0</y-m>

   <z-m>16.41</z-m>

  </center>

  <axis>

   <x>0</x>

   <y>-1</y>

   <z>0</z>

  </axis>

 </animation>
 <animation>

  <type>rotate</type>

  <object-name>Car25</object-name>
  <property>/sim/time/elapsed-sec</property>

  <factor>-2.0</factor>

  <center>

   <x-m>-23.99</x-m>

   <y-m>0</y-m>

   <z-m>20.53</z-m>

  </center>

  <axis>

   <x>0</x>

   <y>-1</y>

   <z>0</z>

  </axis>

 </animation>
 <animation>

  <type>rotate</type>

  <object-name>Car26</object-name>
  <property>/sim/time/elapsed-sec</property>

  <factor>-2.0</factor>

  <center>

   <x-m>-25.15</x-m>

   <y-m>0</y-m>

   <z-m>24.79</z-m>

  </center>

  <axis>

   <x>0</x>

   <y>-1</y>

   <z>0</z>

  </axis>

 </animation>
 <animation>

  <type>rotate</type>

  <object-name>Car27</object-name>
  <property>/sim/time/elapsed-sec</property>

  <factor>-2.0</factor>

  <center>

   <x-m>-25.44</x-m>

   <y-m>0</y-m>

   <z-m>29.26</z-m>

  </center>

  <axis>

   <x>0</x>

   <y>-1</y>

   <z>0</z>

  </axis>

 </animation>
 <animation>

  <type>rotate</type>

  <object-name>Car28</object-name>
  <property>/sim/time/elapsed-sec</property>

  <factor>-2.0</factor>

  <center>

   <x-m>-25.15</x-m>

   <y-m>0</y-m>

   <z-m>33.44</z-m>

  </center>

  <axis>

   <x>0</x>

   <y>-1</y>

   <z>0</z>

  </axis>

 </animation>
 <animation>

  <type>rotate</type>

  <object-name>Car29</object-name>
  <property>/sim/time/elapsed-sec</property>

  <factor>-2.0</factor>

  <center>

   <x-m>-24.03</x-m>

   <y-m>0</y-m>

   <z-m>37.71</z-m>

  </center>

  <axis>

   <x>0</x>

   <y>-1</y>

   <z>0</z>

  </axis>

 </animation>
 <animation>

  <type>rotate</type>

  <object-name>Car30</object-name>
  <property>/sim/time/elapsed-sec</property>

  <factor>-2.0</factor>

  <center>

   <x-m>-22.24</x-m>

   <y-m>0</y-m>

   <z-m>41.83</z-m>

  </center>

  <axis>

   <x>0</x>

   <y>-1</y>

   <z>0</z>

  </axis>

 </animation>
<animation>

  <type>rotate</type>

  <object-name>Car31</object-name>
  <property>/sim/time/elapsed-sec</property>

  <factor>-2.0</factor>

  <center>

   <x-m>-19.66</x-m>

   <y-m>0</y-m>

   <z-m>45.51</z-m>

  </center>

  <axis>

   <x>0</x>

   <y>-1</y>

   <z>0</z>

  </axis>

 </animation>

 <animation>

  <type>rotate</type>

  <object-name>Car32</object-name>
  <property>/sim/time/elapsed-sec</property>

  <factor>-2.0</factor>

  <center>

   <x-m>-16.61</x-m>

   <y-m>0</y-m>

   <z-m>48.65</z-m>

  </center>

  <axis>

   <x>0</x>

   <y>-1</y>

   <z>0</z>

  </axis>

 </animation>
 <animation>

  <type>rotate</type>

  <object-name>Car33</object-name>
  <property>/sim/time/elapsed-sec</property>

  <factor>-2.0</factor>

  <center>

   <x-m>-13</x-m>

   <y-m>0</y-m>

   <z-m>51.22</z-m>

  </center>

  <axis>

   <x>0</x>

   <y>-1</y>

   <z>0</z>

  </axis>

 </animation>
 <animation>

  <type>rotate</type>

  <object-name>Car34</object-name>
  <property>/sim/time/elapsed-sec</property>

  <factor>-2.0</factor>

  <center>

   <x-m>-8.83</x-m>

   <y-m>0</y-m>

   <z-m>53.28</z-m>

  </center>

  <axis>

   <x>0</x>

   <y>-1</y>

   <z>0</z>

  </axis>

 </animation>
 <animation>

  <type>rotate</type>

  <object-name>Car35</object-name>
  <property>/sim/time/elapsed-sec</property>

  <factor>-2.0</factor>

  <center>

   <x-m>-4.53</x-m>

   <y-m>0</y-m>

   <z-m>54.43</z-m>

  </center>

  <axis>

   <x>0</x>

   <y>-1</y>

   <z>0</z>

  </axis>

 </animation>
 <animation>

  <type>rotate</type>

  <object-name>Car36</object-name>
  <property>/sim/time/elapsed-sec</property>

  <factor>-2.0</factor>

  <center>

   <x-m>0.01</x-m>

   <y-m>0</y-m>

   <z-m>54.82</z-m>

  </center>

  <axis>

   <x>0</x>

   <y>-1</y>

   <z>0</z>

  </axis>

 </animation>
 
<animation>
 <type>timed</type>
 <object-name>Wheel2</object-name>
 <object-name>Wheel1</object-name>
 <use-personality type="bool">true</use-personality>
 <branch-duration-sec>
  <random>
   <min>1.5</min>
   <max>1.5</max>
  </random>
 </branch-duration-sec>
 <branch-duration-sec>
  <random>
   <min>1.5</min>
   <max>1.5</max>
  </random>
 </branch-duration-sec>
</animation>

</PropertyList>
